netcop/__init__.py
netcop/parser.py
netcop-1.1.0.dist-info/LICENSE
netcop-1.1.0.dist-info/METADATA
netcop-1.1.0.dist-info/WHEEL
netcop-1.1.0.dist-info/top_level.txt
netcop-1.1.0.dist-info/RECORD
