Metadata-Version: 2.1
Name: netcop
Version: 1.1.0
Summary: A vendor-agnostic parser of network configs
Home-page: https://github.com/andriyanov/netcop
Author: Alexey Andriyanov
Author-email: alanm@bk.ru
Classifier: Programming Language :: Python
Classifier: License :: OSI Approved :: MIT License
Classifier: Operating System :: OS Independent
License-File: LICENSE
